quantify_core/__init__.py
quantify_core/_static_version.py
quantify_core/_version.py
quantify_core/py.typed
quantify_core/analysis/__init__.py
quantify_core/analysis/base_analysis.py
quantify_core/analysis/calibration.py
quantify_core/analysis/conditional_oscillation_analysis.py
quantify_core/analysis/cosine_analysis.py
quantify_core/analysis/fitting_models.py
quantify_core/analysis/interpolation_analysis.py
quantify_core/analysis/optimization_analysis.py
quantify_core/analysis/readout_calibration_analysis.py
quantify_core/analysis/single_qubit_timedomain.py
quantify_core/analysis/spectroscopy_analysis.py
quantify_core/analysis/time_of_flight_analysis.py
quantify_core/analysis/types.py
quantify_core/analysis/schemas/AnalysisSettings.json
quantify_core/analysis/schemas/__init__.py
quantify_core/data/__init__.py
quantify_core/data/dataset_adapters.py
quantify_core/data/dataset_attrs.py
quantify_core/data/experiment.py
quantify_core/data/handling.py
quantify_core/data/types.py
quantify_core/measurement/__init__.py
quantify_core/measurement/control.py
quantify_core/measurement/gettables.py
quantify_core/measurement/types.py
quantify_core/measurement/schemas/Gettable.json
quantify_core/measurement/schemas/Settable.json
quantify_core/measurement/schemas/__init__.py
quantify_core/utilities/__init__.py
quantify_core/utilities/_docs_helpers.py
quantify_core/utilities/_tests_helpers.py
quantify_core/utilities/dataset_examples.py
quantify_core/utilities/deprecation.py
quantify_core/utilities/examples_support.py
quantify_core/utilities/experiment_helpers.py
quantify_core/utilities/general.py
quantify_core/utilities/inspect_utils.py
quantify_core/visualization/SI_utilities.py
quantify_core/visualization/__init__.py
quantify_core/visualization/_appnope.py
quantify_core/visualization/color_utilities.py
quantify_core/visualization/instrument_monitor.py
quantify_core/visualization/mpl_plotting.py
quantify_core/visualization/plot_interpolation.py
quantify_core-0.9.1.dist-info/licenses/AUTHORS.md
quantify_core-0.9.1.dist-info/licenses/LICENSE
quantify_core-0.9.1.dist-info/METADATA
quantify_core-0.9.1.dist-info/WHEEL
quantify_core-0.9.1.dist-info/top_level.txt
quantify_core-0.9.1.dist-info/RECORD
