Metadata-Version: 2.4
Name: quantify-core
Version: 0.9.1
Summary: Quantify-core is a unified quantum computing, solid-state and pulse sequencing physical experimentation framework.
Maintainer-email: Edgar Reehuis <ereehuis@qblox.com>, Robert Sokolewicz <rsokolewicz@qblox.com>, Gábor Oszkár Dénes <gdenes@qblox.com>, Amirtha Varshiny Arumugam <amirthavarshiny@orangeqs.com>, Olga Lebiga <olga@orangeqs.com>
License: BSD-3-Clause
Project-URL: Documentation, https://quantify-os.org/docs/quantify-core
Project-URL: Source, https://gitlab.com/quantify-os/quantify-core
Project-URL: Issue tracker, https://gitlab.com/quantify-os/quantify-core/-/issues
Project-URL: Changelog, https://gitlab.com/quantify-os/quantify-core/-/blob/main/CHANGELOG.md
Project-URL: Slack, https://join.slack.com/t/quantify-hq/shared_invite/zt-1nd78r4e9-rbWdna53cW4DO_YbtMhVuA
Project-URL: Authors, https://gitlab.com/quantify-os/quantify-core/-/blob/main/AUTHORS.md
Keywords: quantum,quantify
Classifier: Development Status :: 4 - Beta
Classifier: Intended Audience :: Developers
Classifier: Intended Audience :: Science/Research
Classifier: License :: OSI Approved :: BSD License
Classifier: Natural Language :: English
Classifier: Programming Language :: Python :: 3
Classifier: Programming Language :: Python :: 3.8
Classifier: Programming Language :: Python :: 3.9
Classifier: Programming Language :: Python :: 3.10
Classifier: Programming Language :: Python :: 3.11
Classifier: Programming Language :: Python :: 3.12
Classifier: Topic :: Scientific/Engineering
Requires-Python: >=3.8
License-File: LICENSE
License-File: AUTHORS.md
Requires-Dist: numpy!=1.19.4
Requires-Dist: qcodes>=0.37.0
Requires-Dist: qcodes-loop
Requires-Dist: scipy!=1.6.0,>=1.5.0
Requires-Dist: h5netcdf
Requires-Dist: xarray[io]>=0.19.0
Requires-Dist: matplotlib!=3.5.0
Requires-Dist: lmfit>=1.0.3
Requires-Dist: pyqt5>5.15.2
Requires-Dist: pyqtgraph
Requires-Dist: jsonschema
Requires-Dist: adaptive
Requires-Dist: filelock
Requires-Dist: appnope
Requires-Dist: uncertainties<v3.2.3
Requires-Dist: dataclasses_json
Requires-Dist: dill
Requires-Dist: methodtools
Requires-Dist: deepdiff
Requires-Dist: scikit-learn
Requires-Dist: typing-extensions
Provides-Extra: test
Requires-Dist: pytest; extra == "test"
Requires-Dist: pytest-mock; extra == "test"
Requires-Dist: pytest-mpl; extra == "test"
Requires-Dist: diff-cover; extra == "test"
Provides-Extra: docs
Requires-Dist: sphinx; extra == "docs"
Requires-Dist: pydata-sphinx-theme; extra == "docs"
Requires-Dist: myst-nb; extra == "docs"
Requires-Dist: rich[jupyter]; extra == "docs"
Requires-Dist: scanpydoc; extra == "docs"
Requires-Dist: sphinx-autodoc-typehints; extra == "docs"
Requires-Dist: sphinx-jsonschema>=1.15; extra == "docs"
Requires-Dist: sphinx-togglebutton; extra == "docs"
Requires-Dist: sphinxcontrib-bibtex; extra == "docs"
Requires-Dist: sphinx-design; extra == "docs"
Requires-Dist: jupyter_sphinx>=0.4.0; extra == "docs"
Provides-Extra: dev
Requires-Dist: quantify-core[docs,test]; extra == "dev"
Requires-Dist: pytest-cov; extra == "dev"
Requires-Dist: pytest-xdist; extra == "dev"
Requires-Dist: nbstripout; extra == "dev"
Requires-Dist: scikit-optimize; extra == "dev"
Requires-Dist: black; extra == "dev"
Requires-Dist: pre-commit; extra == "dev"
Requires-Dist: pre-commit-hooks; extra == "dev"
Requires-Dist: pylint; extra == "dev"
Requires-Dist: pyright; extra == "dev"
Requires-Dist: ruff; extra == "dev"
Requires-Dist: sphinx-autobuild; extra == "dev"
Dynamic: license-file
